{
  "kind": "collectionType",
  "collectionName": "products",
  "info": {
    "singularName": "product",
    "pluralName": "products",
    "displayName": "Product"
  },
  "options": {
    "draftAndPublish": false
  },
  "pluginOptions": {},
  "attributes": {
    "name": {
      "type": "string",
      "required": true,
      "minLength": 5
    },
    "cover_image": {
      "allowedTypes": [
        "images"
      ],
      "type": "media",
      "multiple": false,
      "required": true
    },
    "price": {
      "type": "decimal",
      "required": true,
      "min": 0
    },
    "active": {
      "type": "boolean"
    }
  }
}
